odoo/addons/stock_picking_batch_packaging_qty/README.rst
odoo/addons/stock_picking_batch_packaging_qty/__init__.py
odoo/addons/stock_picking_batch_packaging_qty/__manifest__.py
odoo/addons/stock_picking_batch_packaging_qty/i18n/es.po
odoo/addons/stock_picking_batch_packaging_qty/i18n/it.po
odoo/addons/stock_picking_batch_packaging_qty/i18n/stock_picking_batch_packaging_qty.pot
odoo/addons/stock_picking_batch_packaging_qty/readme/CONFIGURE.md
odoo/addons/stock_picking_batch_packaging_qty/readme/CONTRIBUTORS.md
odoo/addons/stock_picking_batch_packaging_qty/readme/DESCRIPTION.md
odoo/addons/stock_picking_batch_packaging_qty/readme/USAGE.md
odoo/addons/stock_picking_batch_packaging_qty/static/description/icon.png
odoo/addons/stock_picking_batch_packaging_qty/static/description/index.html
odoo/addons/stock_picking_batch_packaging_qty/views/stock_move_line_view.xml
odoo/addons/stock_picking_batch_packaging_qty/views/stock_move_view.xml
odoo_addon_stock_picking_batch_packaging_qty-18.0.1.0.1.dist-info/METADATA
odoo_addon_stock_picking_batch_packaging_qty-18.0.1.0.1.dist-info/WHEEL
odoo_addon_stock_picking_batch_packaging_qty-18.0.1.0.1.dist-info/top_level.txt
odoo_addon_stock_picking_batch_packaging_qty-18.0.1.0.1.dist-info/RECORD
